{"sl_translate":"model,type,mode,racetype,aveh","Count":20,"Total":715,"Missions":[{"MissionId":"6zBkaN-wF0-xPkc5_qJvGA","Content":{"Metadata":{"_id":"6zBkaN-wF0-xPkc5_qJvGA","cat":"none","cdate":"Jul-26-2017 04:06:10","pdate":"2017-07-26T04:06:10Z","data":{"mission":{"gen":{"type":"Race","area":{"z":0,"x":0,"y":0},"char":0,"endtype":0,"min":1,"mtnum":1,"num":6,"rad":0,"rank":1,"start":{"z":12.944,"x":-1675.009,"y":-2848.426},"subtype":7,"tnum":1,"photo":true,"icon":"StuntRaceP2P","mode":"Stunt Race","racetype":"Point To Point","ivm":-431692672,"adverm":0},"race":{"type":"TRIATHLON_P2P","aveh":["Compacts","Coupes","Cycles","Motorcycles","Muscle","Off-Road","Sedans","Sports","Sports Classics","Super","SUVs","Utility","Vans"],"adlc":["7","2047","255","3","16777215","4095","16777215","2097151","1073741823","8191","0","0","31","0","0","0"],"gw":6.5,"chl":[{"x":-1672.026,"y":-2849.861},{"x":-808.995,"y":-3345.462}],"chp":2,"lap":0,"rdis":1990.458,"dist":"1.99 km","ivm":0,"sndchk":[{"x":0,"y":0},{"x":0,"y":0}],"clbs":15359},"weap":{"sub":[],"loc":[],"type":[]},"ene":{"loc":[],"model":[]},"rule":{"liv":0,"pol":1,"score":0,"tdm":0,"time":0,"tod":2,"traf":1,"vdm":0},"prop":{"loc":[{"x":-828.408,"y":-3334.19},{"x":-836.826,"y":-3329.902},{"x":-847.588,"y":-3323.504},{"x":-859.208,"y":-3316.645},{"x":-868.691,"y":-3311.047},{"x":-877.754,"y":-3305.697},{"x":-885.623,"y":-3301.051},{"x":-895.094,"y":-3295.46},{"x":-901.36,"y":-3291.761},{"x":-909.622,"y":-3286.884},{"x":-920.411,"y":-3280.514},{"x":-931.008,"y":-3274.258},{"x":-941.628,"y":-3267.989},{"x":-950.462,"y":-3262.773},{"x":-957.639,"y":-3258.535},{"x":-965.511,"y":-3253.888},{"x":-972.397,"y":-3249.822},{"x":-982.014,"y":-3244.144},{"x":-990.312,"y":-3239.245},{"x":-999.565,"y":-3233.783},{"x":-1009.871,"y":-3228.061},{"x":-1018.767,"y":-3222.808},{"x":-1026.914,"y":-3218.598},{"x":-1034.826,"y":-3213.928},{"x":-1044.011,"y":-3208.505},{"x":-1053.646,"y":-3203.928},{"x":-1060.948,"y":-3199.617},{"x":-1069.73,"y":-3194.432},{"x":-1078.84,"y":-3189.95},{"x":-1088.148,"y":-3185.327},{"x":-1098.174,"y":-3179.407},{"x":-1107.342,"y":-3173.994},{"x":-1116.752,"y":-3169.146},{"x":-1123.922,"y":-3164.913},{"x":-1131.356,"y":-3160.524},{"x":-1137.356,"y":-3156.981},{"x":-1144.524,"y":-3152.749},{"x":-1155.248,"y":-3146.418},{"x":-1164.651,"y":-3140.867},{"x":-1174.034,"y":-3135.327},{"x":-1182.78,"y":-3130.164},{"x":-1191.58,"y":-3124.97},{"x":-1201.549,"y":-3119.085},{"x":-1213.205,"y":-3112.204},{"x":-1224.15,"y":-3107.397},{"x":-1232.026,"y":-3102.746},{"x":-1240.829,"y":-3097.55},{"x":-1251.983,"y":-3090.965},{"x":-1261.777,"y":-3085.184},{"x":-1271.524,"y":-3079.429},{"x":-1278.565,"y":-3075.273},{"x":-1287.813,"y":-3069.813},{"x":-1297.518,"y":-3064.083},{"x":-1304.806,"y":-3059.781},{"x":-1316.011,"y":-3053.821},{"x":-1325.898,"y":-3047.984},{"x":-1333.491,"y":-3043.501},{"x":-1343.032,"y":-3037.869},{"x":-1354.205,"y":-3032.245},{"x":-1365.442,"y":-3025.611},{"x":-1374.872,"y":-3020.044},{"x":-1384.799,"y":-3014.184},{"x":-1394.261,"y":-3008.597},{"x":-1404.391,"y":-3002.617},{"x":-1416.148,"y":-2995.677},{"x":-1428.356,"y":-2988.47},{"x":-1441.773,"y":-2982.255},{"x":-1452.86,"y":-2975.71},{"x":-1463.164,"y":-2969.627},{"x":-1470.906,"y":-2965.058},{"x":-1477.547,"y":-2961.136},{"x":-1487.075,"y":-2955.511},{"x":-1495.694,"y":-2950.422},{"x":-1501.606,"y":-2946.933},{"x":-1508.517,"y":-2942.852},{"x":-1517.672,"y":-2937.448},{"x":-1526.479,"y":-2932.249},{"x":-1533.625,"y":-2928.031},{"x":-1538.785,"y":-2924.984},{"x":-1545.422,"y":-2921.066},{"x":-1554.796,"y":-2915.531},{"x":-1564.15,"y":-2910.009},{"x":-1575.06,"y":-2903.568},{"x":-1581.303,"y":-2899.883},{"x":-1591.224,"y":-2894.025},{"x":-1601.559,"y":-2887.923},{"x":-1612.581,"y":-2882.017},{"x":-1624.881,"y":-2877.601},{"x":-1631.649,"y":-2873.604},{"x":-1638.312,"y":-2869.671},{"x":-1645.132,"y":-2865.645},{"x":-1654,"y":-2860.409},{"x":-1663.335,"y":-2854.898},{"x":-1672.349,"y":-2849.577}],"model":["Neon Tube Short","Speed Boost Track","Speed Boost Track","Speed Boost Track","Speed Boost Track","Speed Boost Track","Speed Boost Track","Speed Boost Track","Speed Boost Track","Speed Boost Track","Speed Boost Track","Speed Boost Track","Speed Boost Track","Speed Boost Track","Speed Boost Track","Speed Boost Track","Speed Boost Track","Speed Boost Track","Speed Boost Track","Speed Boost Track","Speed Boost Track","Speed Boost Track","Speed Boost Track","Speed Boost Track","Speed Boost Track","Speed Boost Track","Speed Boost Track","Speed Boost Track","Speed Boost Track","Speed Boost Track","Speed Boost Track","Speed Boost Track","Speed Boost Track","Speed Boost Track","Speed Boost Track","Speed Boost Track","Speed Boost Track","Speed Boost Track","Speed Boost Track","Speed Boost Track","Speed Boost Track","Speed Boost Track","Speed Boost Track","Speed Boost Track","Speed Boost Track","Speed Boost Track","Speed Boost Track","Speed Boost Track","Speed Boost Track","Speed Boost Track","Speed Boost Track","Speed Boost Track","Speed Boost Track","Speed Boost Track","Speed Boost Track","Speed Boost Track","Speed Boost Track","Speed Boost Track","Speed Boost Track","Speed Boost Track","Speed Boost Track","Speed Boost Track","Speed Boost Track","Speed Boost Track","Speed Boost Track","Speed Boost Track","Speed Boost Track","Speed Boost Track","Speed Boost Track","Speed Boost Track","Speed Boost Track","Speed Boost Track","Speed Boost Track","Speed Boost Track","Speed Boost Track","Speed Boost Track","Speed Boost Track","Speed Boost Track","Speed Boost Track","Speed Boost Track","Speed Boost Track","Speed Boost Track","Speed Boost Track","Speed Boost Track","Speed Boost Track","Speed Boost Track","Speed Boost Track","Speed Boost Track","Speed Boost Track","Speed Boost Track","Speed Boost Track","Speed Boost Track","Speed Boost Track","Speed Boost Track"]},"dprop":{"loc":[],"model":[]},"veh":{"loc":[{"x":-1677.635,"y":-2843.272},{"x":-1685.898,"y":-2846.449},{"x":-1688.133,"y":-2837.883},{"x":-1696.396,"y":-2841.06},{"x":-1698.63,"y":-2832.493},{"x":-1706.893,"y":-2835.67}],"model":["Vehicle: 0","Vehicle: 0","Vehicle: 0","Vehicle: 0","Vehicle: 0","Vehicle: 0"]},"obj":{"loc":[],"model":[],"obb":[]},"endcon":{"dpos0":[]}},"meta":{"ems":false,"loc":[],"locn":[],"mrule":[],"stinv":[],"veh":[0],"vehcl":["Industrial","","Special"],"wp":[],"wpcl":[]}},"latest":true,"latestVersionContentId":"6zBkaN-wF0-xPkc5_qJvGA","name":"CHROME FARM","desc":"FARM FOR CHROME MONEY AND A BIT OF XP","nickname":"Crepeecraller","avatar":"n/crepeecraller","rockstarId":"67547754","isOwner":false,"creatorMedal":"bronze","crewurl":"/crew/creiepycrew","crewtag":"Crpy","crewrank":1,"crewcolor":"#003399","isfoundercrew":false,"isprivate":true,"thumbnail":"https://prod.cloud.rockstargames.com/ugc/gta5mission/6491/6zBkaN-wF0-xPkc5_qJvGA/2_0.jpg","plat":"PC","cansubscribe":false,"subscribed":false,"tags":[],"ver":6,"url":"/games/gtav/jobs/job/6zBkaN-wF0-xPkc5_qJvGA","bkmk":false,"RootContentId":"N1ISwhHFbU2zEywiWw1PnQ"},"stats":{"dt":0,"du":0,"pt":19,"pu":4,"qt":0,"qu":0},"ratings":{"rt_tot":0,"bkmk_unq":4,"rt_pos":2,"rt_pos_pct":0.6666667,"rt_unq":3,"rt_neg":1,"rt_neg_pct":0.333333343,"rt_avg":0.6666667,"avg":"67%"}},"Players":[]},{"MissionId":"PKUkhB7jzkyzx3dW3ImykQ","Content":{"Metadata":{"_id":"PKUkhB7jzkyzx3dW3ImykQ","cat":"none","cdate":"Jul-26-2017 02:52:57","pdate":"2017-07-26T03:16:20Z","data":{"mission":{"gen":{"type":"FreeMission","char":0,"endtype":0,"min":2,"mtnum":1,"num":30,"rad":0,"rank":1,"start":{"z":261.85,"x":140.37,"y":-628.98},"subtype":5,"tnum":2,"photo":false,"icon":"LastTeamStanding","mode":"Last Team Standing","ivm":-1,"adverm":0},"rule":{"liv":0,"pol":1,"score":0,"tdm":0,"time":0,"tod":0,"traf":2,"vdm":0}},"meta":{"ems":false,"loc":["PBOX"],"mrule":[0,18],"veh":[-956048545,1581459400]}},"latest":true,"latestVersionContentId":"PKUkhB7jzkyzx3dW3ImykQ","name":"Taxis vs Uber","desc":"Por un trabajo justo","nickname":"LordBunch","avatar":"n/lordbunch","rockstarId":"79082885","isOwner":false,"creatorMedal":"silver","crewurl":"/crew/fcol_fuerza_colombia","crewtag":"FCOL","crewrank":4,"crewcolor":"#0313fa","isfoundercrew":false,"isprivate":true,"thumbnail":"https://prod.cloud.rockstargames.com/ugc/gta5mission/7815/PKUkhB7jzkyzx3dW3ImykQ/2_0.jpg","plat":"PC","cansubscribe":false,"subscribed":false,"tags":[],"ver":1,"url":"/games/gtav/jobs/job/PKUkhB7jzkyzx3dW3ImykQ","bkmk":false,"RootContentId":"PKUkhB7jzkyzx3dW3ImykQ"},"stats":{"dt":0,"du":0,"pt":3,"pu":2,"qt":0,"qu":0},"ratings":{"rt_tot":0,"bkmk_unq":2,"rt_pos":2,"rt_pos_pct":1,"rt_unq":2,"rt_neg":0,"rt_neg_pct":0,"rt_avg":1,"avg":"100%"}},"Players":[]},{"MissionId":"O3Sbvj4f1kKdbPiak5eCxw","Content":{"Metadata":{"_id":"O3Sbvj4f1kKdbPiak5eCxw","cat":"none","cdate":"Jul-26-2017 09:17:26","pdate":"2017-07-26T09:30:28Z","data":{"mission":{"gen":{"type":"Race","char":0,"endtype":0,"min":1,"mtnum":1,"num":22,"rad":0,"rank":1,"start":{"z":32.83,"x":1151.58,"y":3629.16},"subtype":6,"tnum":1,"photo":false,"icon":"StuntRace","mode":"Stunt Race","racetype":"Laps","ivm":2067820283,"adverm":0},"race":{"type":"STANDARD","aveh":[],"gw":0,"chp":14,"lap":3,"rdis":3613.527,"dist":"3.61 km","ivm":0,"clbs":1023},"rule":{"liv":0,"pol":1,"score":0,"tdm":0,"time":0,"tod":2,"traf":1,"vdm":0}},"meta":{"ems":false,"loc":["DESRT","MTCHIL","SANDY"],"veh":[0],"vehcl":["","Cycles","Industrial","Special","Utility","Vans"]}},"latest":true,"latestVersionContentId":"O3Sbvj4f1kKdbPiak5eCxw","name":"F1 Monza","copiedFrom":"XPkjyUSi5EGjHEQuGEbDeQ","desc":"F1 circuit, enjoy racing on that legendary circuit and please do not cut corners.","nickname":"SchwestrCZ","avatar":"n/schwestrcz","rockstarId":"66313322","isOwner":false,"creatorMedal":"silver","crewurl":"/crew/energy_drink_monster","crewtag":"mstr","crewrank":4,"crewcolor":"#14ff03","isfoundercrew":false,"isprivate":true,"thumbnail":"https://prod.cloud.rockstargames.com/ugc/gta5mission/9556/O3Sbvj4f1kKdbPiak5eCxw/2_0.jpg","plat":"PC","cansubscribe":false,"subscribed":false,"tags":["monza f1"],"ver":1,"url":"/games/gtav/jobs/job/O3Sbvj4f1kKdbPiak5eCxw","bkmk":false,"RootContentId":"O3Sbvj4f1kKdbPiak5eCxw"},"stats":{"dt":0,"du":0,"pt":2,"pu":2,"qt":0,"qu":0},"ratings":{"rt_tot":0,"bkmk_unq":0,"rt_pos":2,"rt_pos_pct":1,"rt_unq":2,"rt_neg":0,"rt_neg_pct":0,"rt_avg":1,"avg":"100%"}},"Players":[]},{"MissionId":"Kt4NcVLqGkug4e6yg8jUng","Content":{"Metadata":{"_id":"Kt4NcVLqGkug4e6yg8jUng","cat":"none","cdate":"Jul-26-2017 13:24:55","pdate":"2017-07-26T13:25:04Z","data":{"mission":{"gen":{"type":"Race","char":0,"endtype":0,"min":1,"mtnum":1,"num":2,"rad":0,"rank":1,"start":{"z":44.67,"x":2178.43,"y":3429.2},"subtype":6,"tnum":1,"photo":false,"icon":"StuntRace","mode":"Stunt Race","racetype":"Laps","ivm":-1829802492,"adverm":0},"race":{"type":"STANDARD","aveh":[],"gw":0,"chp":9,"lap":0,"rdis":1907.665,"dist":"1.91 km","ivm":0,"clbs":384},"rule":{"liv":0,"pol":1,"score":0,"tdm":0,"time":0,"tod":3,"traf":0,"vdm":0}},"meta":{"ems":false,"loc":["ALAMO"],"veh":[0],"vehcl":["","Classics","Compacts","Coupes","Cycles","Industrial","Mucle","OffRoad","Sedans","Special","Sports","SUV","Utility","Vans"]}},"latest":true,"latestVersionContentId":"Kt4NcVLqGkug4e6yg8jUng","name":"long","desc":"qwasd","nickname":"sukag103","avatar":"n/sukag103","rockstarId":"86282012","isOwner":false,"creatorMedal":"platinum","crewurl":"/crew/od_clan_yt","crewtag":"ODYT","crewrank":4,"crewcolor":"#6600CC","isfoundercrew":false,"isprivate":true,"thumbnail":"https://prod.cloud.rockstargames.com/ugc/gta5mission/6693/Kt4NcVLqGkug4e6yg8jUng/2_0.jpg","plat":"PC","cansubscribe":false,"subscribed":false,"tags":[],"ver":1,"url":"/games/gtav/jobs/job/Kt4NcVLqGkug4e6yg8jUng","bkmk":false,"RootContentId":"Kt4NcVLqGkug4e6yg8jUng"},"stats":{"dt":0,"du":0,"pt":6,"pu":2,"qt":0,"qu":0},"ratings":{"rt_tot":0,"bkmk_unq":0,"rt_pos":2,"rt_pos_pct":1,"rt_unq":2,"rt_neg":0,"rt_neg_pct":0,"rt_avg":1,"avg":"100%"}},"Players":[]},{"MissionId":"GvbQ5inO1UyA_HD0Tn8ypg","Content":{"Metadata":{"_id":"GvbQ5inO1UyA_HD0Tn8ypg","cat":"none","cdate":"Jul-26-2017 14:16:10","pdate":"2017-07-26T14:16:29Z","data":{"mission":{"gen":{"type":"Race","char":0,"endtype":0,"min":1,"mtnum":1,"num":2,"rad":0,"rank":1,"start":{"z":58.18,"x":1561.98,"y":-989.7},"subtype":1,"tnum":1,"photo":false,"icon":"LandRaceP2P","mode":"Land Race","racetype":"Point To Point","ivm":0,"adverm":0},"race":{"type":"STANDARD","aveh":[],"gw":0,"chp":15,"lap":0,"rdis":1052.91,"dist":"1.05 km","ivm":0,"clbs":15359},"rule":{"liv":0,"pol":1,"score":0,"tdm":0,"time":0,"tod":0,"traf":0,"vdm":0}},"meta":{"ems":false,"loc":["TATAMO"],"veh":[0],"vehcl":["","Industrial","Special"]}},"latest":true,"latestVersionContentId":"GvbQ5inO1UyA_HD0Tn8ypg","name":"For Derek","desc":"For U","nickname":"MAD_WINS","avatar":"n/mad_wins","rockstarId":"37662318","isOwner":false,"creatorMedal":"bronze","crewurl":"/crew/man_of_the_world","crewtag":"motw","crewrank":0,"crewcolor":"#03ffff","isfoundercrew":false,"isprivate":true,"thumbnail":"https://prod.cloud.rockstargames.com/ugc/gta5mission/0533/GvbQ5inO1UyA_HD0Tn8ypg/2_0.jpg","plat":"PC","cansubscribe":false,"subscribed":false,"tags":[],"ver":1,"url":"/games/gtav/jobs/job/GvbQ5inO1UyA_HD0Tn8ypg","bkmk":false,"RootContentId":"GvbQ5inO1UyA_HD0Tn8ypg"},"stats":{"dt":0,"du":0,"pt":44,"pu":2,"qt":0,"qu":0},"ratings":{"rt_tot":0,"bkmk_unq":0,"rt_pos":2,"rt_pos_pct":1,"rt_unq":2,"rt_neg":0,"rt_neg_pct":0,"rt_avg":1,"avg":"100%"}},"Players":[]},{"MissionId":"obliPHbU80WUiP_UBzpIhw","Content":{"Metadata":{"_id":"obliPHbU80WUiP_UBzpIhw","cat":"none","cdate":"Jul-26-2017 14:25:42","pdate":"2017-07-26T14:25:47Z","data":{"mission":{"gen":{"type":"Deathmatch","char":0,"endtype":0,"min":2,"mtnum":1,"num":4,"rad":0,"rank":1,"start":{"z":168.47,"x":-2334.75,"y":273.01},"subtype":0,"tnum":4,"photo":false,"icon":"Deathmatch","mode":"Deathmatch","ivm":0,"adverm":0},"rule":{"liv":0,"pol":1,"score":0,"tdm":0,"time":6,"tod":3,"traf":1,"vdm":0}},"meta":{"ems":false,"loc":["","SanAnd"]}},"latest":true,"latestVersionContentId":"obliPHbU80WUiP_UBzpIhw","name":"Im labyrint","desc":"Findet euch im Labyrint. Vorher karte und HUD ausmachen","nickname":"OXMultiMaxXO","avatar":"n/oxmultimaxxo","rockstarId":"81836734","isOwner":false,"creatorMedal":"white","crewurl":"/crew/shield_branch","crewtag":"SHDC","crewrank":4,"crewcolor":"#090299","isfoundercrew":false,"isprivate":true,"thumbnail":"https://prod.cloud.rockstargames.com/ugc/gta5mission/9663/obliPHbU80WUiP_UBzpIhw/2_0.jpg","plat":"PC","cansubscribe":false,"subscribed":false,"tags":[],"ver":1,"url":"/games/gtav/jobs/job/obliPHbU80WUiP_UBzpIhw","bkmk":false,"RootContentId":"obliPHbU80WUiP_UBzpIhw"},"stats":{"dt":0,"du":0,"pt":2,"pu":2,"qt":0,"qu":0},"ratings":{"rt_tot":0,"bkmk_unq":0,"rt_pos":2,"rt_pos_pct":1,"rt_unq":2,"rt_neg":0,"rt_neg_pct":0,"rt_avg":1,"avg":"100%"}},"Players":[]},{"MissionId":"KpixRKj5K0uF48Hha6FIZQ","Content":{"Metadata":{"_id":"KpixRKj5K0uF48Hha6FIZQ","cat":"none","cdate":"Jul-26-2017 15:46:09","pdate":"2017-07-26T15:46:09Z","data":{"mission":{"gen":{"type":"Race","char":0,"endtype":0,"min":1,"mtnum":1,"num":8,"rad":0,"rank":1,"start":{"z":28.2,"x":189.96,"y":-1255.15},"subtype":7,"tnum":1,"photo":false,"icon":"StuntRaceP2P","mode":"Stunt Race","racetype":"Point To Point","ivm":1939284556,"adverm":0},"race":{"type":"STANDARD","aveh":[],"gw":0,"chp":19,"lap":0,"rdis":5940.283,"dist":"5.94 km","ivm":0,"clbs":192},"rule":{"liv":0,"pol":1,"score":0,"tdm":0,"time":0,"tod":1,"traf":1,"vdm":0}},"meta":{"ems":false,"loc":["EBURO","LMESA","MIRR","MURRI","PALHIGH"],"veh":[0],"vehcl":["","Bikes","Classics","Compacts","Coupes","Cycles","Industrial","Mucle","OffRoad","Sedans","Special","SUV","Utility","Vans"]}},"latest":true,"latestVersionContentId":"KpixRKj5K0uF48Hha6FIZQ","name":"Hard work just for a fren","desc":"Duck you for making me make this you blunt, I hope you enjoy because this literally took me like 2 hourse you blunt!","nickname":"Classy_Pug","avatar":"n/classy_pug","rockstarId":"90724979","isOwner":false,"creatorMedal":"silver","crewurl":"/crew/the_ls_m0bb","crewtag":"w33d","crewrank":4,"crewcolor":"#840AFF","isfoundercrew":false,"isprivate":true,"thumbnail":"https://prod.cloud.rockstargames.com/ugc/gta5mission/1120/KpixRKj5K0uF48Hha6FIZQ/2_0.jpg","plat":"PC","cansubscribe":false,"subscribed":false,"tags":[],"ver":1,"url":"/games/gtav/jobs/job/KpixRKj5K0uF48Hha6FIZQ","bkmk":false,"RootContentId":"KpixRKj5K0uF48Hha6FIZQ"},"stats":{"dt":0,"du":0,"pt":2,"pu":2,"qt":0,"qu":0},"ratings":{"rt_tot":0,"bkmk_unq":0,"rt_pos":2,"rt_pos_pct":1,"rt_unq":2,"rt_neg":0,"rt_neg_pct":0,"rt_avg":1,"avg":"100%"}},"Players":[]},{"MissionId":"XFBu8Ay61kK30t4mGqQBEA","Content":{"Metadata":{"_id":"XFBu8Ay61kK30t4mGqQBEA","cat":"none","cdate":"Jul-26-2017 07:17:02","pdate":"2017-07-26T07:17:02Z","data":{"mission":{"gen":{"type":"Race","char":0,"endtype":0,"min":1,"mtnum":1,"num":8,"rad":0,"rank":1,"start":{"z":69.98,"x":-941.69,"y":304.08},"subtype":1,"tnum":1,"photo":false,"icon":"LandRaceP2P","mode":"Land Race","racetype":"Point To Point","ivm":0,"adverm":0},"race":{"type":"STANDARD","aveh":[],"gw":0,"chp":58,"lap":0,"rdis":3358.303,"dist":"3.36 km","ivm":0,"clbs":11263},"rule":{"liv":0,"pol":1,"score":0,"tdm":0,"time":0,"tod":0,"traf":0,"vdm":0}},"meta":{"ems":false,"loc":["ALTA","BURTON","EAST_V","HAWICK","LMESA","WVINE"],"veh":[0],"vehcl":["","Industrial","Special","Vans"]}},"latest":true,"latestVersionContentId":"XFBu8Ay61kK30t4mGqQBEA","name":"Лос-Сантос.Спорткар","desc":"Посмотрите красоты vinewood и на ужасы кварталов.","nickname":"LOOTER_MC_","avatar":"n/looter_mc_","rockstarId":"106039630","isOwner":false,"creatorMedal":"gold","crewrank":0,"isfoundercrew":false,"isprivate":false,"thumbnail":"https://prod.cloud.rockstargames.com/ugc/gta5mission/8050/XFBu8Ay61kK30t4mGqQBEA/2_0.jpg","plat":"PC","cansubscribe":false,"subscribed":false,"tags":[],"ver":1,"url":"/games/gtav/jobs/job/XFBu8Ay61kK30t4mGqQBEA","bkmk":false,"RootContentId":"XFBu8Ay61kK30t4mGqQBEA"},"stats":{"dt":0,"du":0,"pt":2,"pu":2,"qt":0,"qu":0},"ratings":{"rt_tot":0,"bkmk_unq":0,"rt_pos":2,"rt_pos_pct":1,"rt_unq":2,"rt_neg":0,"rt_neg_pct":0,"rt_avg":1,"avg":"100%"}},"Players":[]},{"MissionId":"A7jU26CzzE-AZsYOPRFAwA","Content":{"Metadata":{"_id":"A7jU26CzzE-AZsYOPRFAwA","cat":"none","cdate":"Jul-26-2017 18:12:30","pdate":"2017-07-26T18:12:30Z","data":{"mission":{"gen":{"type":"Race","char":0,"endtype":0,"min":1,"mtnum":1,"num":10,"rad":0,"rank":1,"start":{"z":48.66,"x":1084.06,"y":2280.87},"subtype":0,"tnum":1,"photo":false,"icon":"LandRace","mode":"Land Race","racetype":"Laps","ivm":-845961253,"adverm":0},"race":{"type":"STANDARD","aveh":[],"gw":0,"chp":42,"lap":1,"rdis":1875.533,"dist":"1.88 km","ivm":0,"clbs":10752},"rule":{"liv":0,"pol":1,"score":0,"tdm":0,"time":0,"tod":0,"traf":0,"vdm":0}},"meta":{"ems":false,"veh":[0],"vehcl":["","Bikes","Classics","Compacts","Coupes","Industrial","Mucle","Sedans","Special","Sports","Super","SUV","Vans"]}},"latest":true,"latestVersionContentId":"A7jU26CzzE-AZsYOPRFAwA","name":"Motster Truck Rampage","desc":"TRUUUUUUCKS!!!","nickname":"Talladega499","avatar":"n/talladega499","rockstarId":"24282400","isOwner":false,"creatorMedal":"platinum","crewurl":"/crew/hateful_ducks","crewtag":"DUCK","crewrank":4,"crewcolor":"#e335c0","isfoundercrew":false,"isprivate":true,"thumbnail":"https://prod.cloud.rockstargames.com/ugc/gta5mission/7604/A7jU26CzzE-AZsYOPRFAwA/2_0.jpg","plat":"PC","cansubscribe":false,"subscribed":false,"tags":[],"ver":1,"url":"/games/gtav/jobs/job/A7jU26CzzE-AZsYOPRFAwA","bkmk":false,"RootContentId":"A7jU26CzzE-AZsYOPRFAwA"},"stats":{"dt":0,"du":0,"pt":2,"pu":2,"qt":0,"qu":0},"ratings":{"rt_tot":0,"bkmk_unq":0,"rt_pos":2,"rt_pos_pct":1,"rt_unq":2,"rt_neg":0,"rt_neg_pct":0,"rt_avg":1,"avg":"100%"}},"Players":[]},{"MissionId":"eXj4GCDoC02gOJ69k0nqJA","Content":{"Metadata":{"_id":"eXj4GCDoC02gOJ69k0nqJA","cat":"none","cdate":"Jul-26-2017 01:27:51","pdate":"2017-07-26T01:27:52Z","data":{"mission":{"gen":{"type":"Race","char":0,"endtype":0,"min":1,"mtnum":1,"num":24,"rad":0,"rank":1,"start":{"z":784.36,"x":476.28,"y":5540.33},"subtype":6,"tnum":1,"photo":false,"icon":"StuntRace","mode":"Special Vehicle Race","racetype":"Laps","ivm":941494461,"adverm":0},"race":{"type":"STANDARD","aveh":[],"gw":0,"chp":4,"lap":1,"rdis":2081.87,"dist":"2.08 km","ivm":0,"clbs":32768},"rule":{"liv":0,"pol":1,"score":0,"tdm":0,"time":0,"tod":0,"traf":0,"vdm":0}},"meta":{"ems":false,"veh":[0],"vehcl":["","Bikes","Classics","Compacts","Coupes","Cycles","Industrial","Mucle","OffRoad","Sedans","Sports","Super","SUV","Utility","Vans"]}},"latest":true,"latestVersionContentId":"eXj4GCDoC02gOJ69k0nqJA","name":"Ruiner 2000 - Loop","desc":"First person is suggested for the actual loop since your camera will be correct. On the last part before you commit suicide off the ledge, drift around and parachute.","nickname":"SirSmedic","avatar":"n/sirsmedic","rockstarId":"87370012","isOwner":false,"creatorMedal":"gold","crewurl":"/crew/ign_crew","crewtag":"IGN","crewrank":1,"crewcolor":"#f99d27","isfoundercrew":false,"isprivate":false,"thumbnail":"https://prod.cloud.rockstargames.com/ugc/gta5mission/5910/eXj4GCDoC02gOJ69k0nqJA/2_0.jpg","plat":"PC","cansubscribe":false,"subscribed":false,"tags":["fast","loop","ruiner 2000"],"ver":3,"url":"/games/gtav/jobs/job/eXj4GCDoC02gOJ69k0nqJA","bkmk":false,"RootContentId":"brqlaHLNgESaemvLwiaEvQ"},"stats":{"dt":0,"du":0,"pt":2,"pu":2,"qt":0,"qu":0},"ratings":{"rt_tot":0,"bkmk_unq":1,"rt_pos":2,"rt_pos_pct":1,"rt_unq":2,"rt_neg":0,"rt_neg_pct":0,"rt_avg":1,"avg":"100%"}},"Players":[]},{"MissionId":"Mxk2TzgQ0U2GzdNdp9br2w","Content":{"Metadata":{"_id":"Mxk2TzgQ0U2GzdNdp9br2w","cat":"none","cdate":"Jul-26-2017 08:49:55","pdate":"2017-07-26T08:49:56Z","data":{"mission":{"gen":{"type":"FreeMission","char":0,"endtype":0,"min":4,"mtnum":1,"num":4,"rad":0,"rank":1,"start":{"z":69.38,"x":-601.89,"y":5314.67},"subtype":5,"tnum":4,"photo":false,"icon":"LastTeamStanding","mode":"Last Team Standing","ivm":-1,"adverm":0},"rule":{"liv":0,"pol":1,"score":0,"tdm":0,"time":0,"tod":2,"traf":0,"vdm":0}},"meta":{"ems":false,"loc":["MTCHIL"],"mrule":[18],"wp":[-1965167499,-1888453608,1311775952,1632369836]}},"latest":true,"latestVersionContentId":"Mxk2TzgQ0U2GzdNdp9br2w","name":"來對決吧 吳宗謙","desc":"殺宗謙就好","nickname":"MID901026","avatar":"n/mid901026","rockstarId":"67828200","isOwner":false,"creatorMedal":"white","crewurl":"/crew/flop_failure","crewtag":"dead","crewrank":0,"crewcolor":"#1e27a8","isfoundercrew":false,"isprivate":true,"thumbnail":"https://prod.cloud.rockstargames.com/ugc/gta5mission/4785/Mxk2TzgQ0U2GzdNdp9br2w/2_0.jpg","plat":"PC","cansubscribe":false,"subscribed":false,"tags":[],"ver":3,"url":"/games/gtav/jobs/job/Mxk2TzgQ0U2GzdNdp9br2w","bkmk":false,"RootContentId":"WNzL9k_f6EmzT8KXsVHP2w"},"stats":{"dt":0,"du":0,"pt":7,"pu":4,"qt":0,"qu":0},"ratings":{"rt_tot":0,"bkmk_unq":0,"rt_pos":2,"rt_pos_pct":0.5,"rt_unq":4,"rt_neg":2,"rt_neg_pct":0.5,"rt_avg":0.5,"avg":"50%"}},"Players":[]},{"MissionId":"PpORB22U0065BXEbUopjoQ","Content":{"Metadata":{"_id":"PpORB22U0065BXEbUopjoQ","cat":"none","cdate":"Jul-26-2017 03:12:28","pdate":"2017-07-26T03:12:28Z","data":{"mission":{"gen":{"type":"FreeMission","char":0,"endtype":2,"min":2,"mtnum":1,"num":2,"rad":0,"rank":1,"start":{"z":40.15,"x":1736.39,"y":3290.74},"subtype":6,"tnum":2,"photo":false,"icon":"Capture","mode":"Capture","ivm":-1,"adverm":0},"rule":{"liv":0,"pol":1,"score":0,"tdm":0,"time":0,"tod":1,"traf":1,"vdm":0}},"meta":{"ems":true,"loc":["WVINE"],"mrule":[0,2,11],"veh":[-1205801634,-50547061,729783779,970385471,1824333165],"wp":[-1118969278]}},"latest":true,"latestVersionContentId":"PpORB22U0065BXEbUopjoQ","name":"SpaceZ Training","desc":"A training mission for the Raptor Armanents Aerospace Association. It&#39;s not really meant to be played in the typical way for a capture, but do whatever you want.","nickname":"IAmASandwich","avatar":"n/iamasandwich","rockstarId":"60511241","isOwner":false,"creatorMedal":"white","crewurl":"/crew/bc_defense_services","crewtag":"BCDS","crewrank":0,"crewcolor":"#cd9f66","isfoundercrew":false,"isprivate":true,"thumbnail":"https://prod.cloud.rockstargames.com/ugc/gta5mission/3819/PpORB22U0065BXEbUopjoQ/2_0.jpg","plat":"PC","cansubscribe":false,"subscribed":false,"tags":[],"ver":3,"url":"/games/gtav/jobs/job/PpORB22U0065BXEbUopjoQ","bkmk":false,"RootContentId":"giq_YrzqJkOwCuqsYunqMw"},"stats":{"dt":0,"du":0,"pt":6,"pu":2,"qt":0,"qu":0},"ratings":{"rt_tot":0,"bkmk_unq":0,"rt_pos":2,"rt_pos_pct":1,"rt_unq":2,"rt_neg":0,"rt_neg_pct":0,"rt_avg":1,"avg":"100%"}},"Players":[]},{"MissionId":"JObmeynEYEytIc_lEFNesg","Content":{"Metadata":{"_id":"JObmeynEYEytIc_lEFNesg","cat":"none","cdate":"Jul-26-2017 02:47:08","pdate":"2017-07-26T02:47:08Z","data":{"mission":{"gen":{"type":"Race","char":0,"endtype":0,"min":1,"mtnum":1,"num":2,"rad":0,"rank":1,"start":{"z":53.49,"x":87.21,"y":-205.27},"subtype":7,"tnum":1,"photo":false,"icon":"StuntRaceP2P","mode":"Stunt Race","racetype":"Point To Point","ivm":408192225,"adverm":0},"race":{"type":"STANDARD","aveh":[],"gw":0,"chp":2,"lap":0,"rdis":1011.44,"dist":"1.01 km","ivm":0,"clbs":128},"rule":{"liv":0,"pol":1,"score":0,"tdm":0,"time":0,"tod":0,"traf":1,"vdm":0}},"meta":{"ems":false,"loc":["BURTON","HAWICK"],"veh":[0],"vehcl":["","Bikes","Classics","Compacts","Coupes","Cycles","Industrial","Mucle","OffRoad","Sedans","Special","Sports","SUV","Utility","Vans"]}},"latest":true,"latestVersionContentId":"JObmeynEYEytIc_lEFNesg","name":"The fast and the grinding","desc":"For the grinders.","nickname":"ThePeterDude","avatar":"n/thepeterdude","rockstarId":"80208164","isOwner":false,"creatorMedal":"gold","crewurl":"/crew/thedankbeasts","crewtag":"TDbC","crewrank":0,"crewcolor":"#f00f03","isfoundercrew":false,"isprivate":true,"thumbnail":"https://prod.cloud.rockstargames.com/ugc/gta5mission/2312/JObmeynEYEytIc_lEFNesg/2_0.jpg","plat":"PC","cansubscribe":false,"subscribed":false,"tags":[],"ver":1,"url":"/games/gtav/jobs/job/JObmeynEYEytIc_lEFNesg","bkmk":false,"RootContentId":"JObmeynEYEytIc_lEFNesg"},"stats":{"dt":0,"du":0,"pt":28,"pu":2,"qt":0,"qu":0},"ratings":{"rt_tot":0,"bkmk_unq":0,"rt_pos":2,"rt_pos_pct":1,"rt_unq":2,"rt_neg":0,"rt_neg_pct":0,"rt_avg":1,"avg":"100%"}},"Players":[]},{"MissionId":"HFmQT5AjF0SnST8f1pZ_KA","Content":{"Metadata":{"_id":"HFmQT5AjF0SnST8f1pZ_KA","cat":"none","cdate":"Jul-26-2017 12:05:54","pdate":"2017-07-26T12:09:09Z","data":{"mission":{"gen":{"type":"Race","char":0,"endtype":0,"min":1,"mtnum":1,"num":4,"rad":0,"rank":1,"start":{"z":16.91,"x":-2731.18,"y":2309.5},"subtype":1,"tnum":1,"photo":false,"icon":"LandRaceP2P","mode":"Land Race","racetype":"Point To Point","ivm":0,"adverm":0},"race":{"type":"STANDARD","aveh":[],"gw":0,"chp":2,"lap":0,"rdis":1097.224,"dist":"1.10 km","ivm":0,"clbs":1023},"rule":{"liv":0,"pol":1,"score":0,"tdm":0,"time":0,"tod":1,"traf":1,"vdm":0}},"meta":{"ems":false,"loc":["NCHU"],"veh":[0],"vehcl":["","Cycles","Industrial","Special","Utility","Vans"]}},"latest":true,"latestVersionContentId":"HFmQT5AjF0SnST8f1pZ_KA","name":"Rennschule L1","desc":"&#220;bung #1 Starten","nickname":"Shadowana","avatar":"n/shadowana","rockstarId":"64919580","isOwner":false,"creatorMedal":"silver","crewurl":"/crew/headhunters4-ever","crewtag":"HeHu","crewrank":4,"crewcolor":"#990202","isfoundercrew":false,"isprivate":true,"thumbnail":"https://prod.cloud.rockstargames.com/ugc/gta5mission/8695/HFmQT5AjF0SnST8f1pZ_KA/2_0.jpg","plat":"PC","cansubscribe":false,"subscribed":false,"tags":["shadowana"],"ver":1,"url":"/games/gtav/jobs/job/HFmQT5AjF0SnST8f1pZ_KA","bkmk":false,"RootContentId":"HFmQT5AjF0SnST8f1pZ_KA"},"stats":{"dt":0,"du":0,"pt":2,"pu":2,"qt":0,"qu":0},"ratings":{"rt_tot":0,"bkmk_unq":0,"rt_pos":2,"rt_pos_pct":1,"rt_unq":2,"rt_neg":0,"rt_neg_pct":0,"rt_avg":1,"avg":"100%"}},"Players":[]},{"MissionId":"CpzssonmGkSHHB2bLOeC-Q","Content":{"Metadata":{"_id":"CpzssonmGkSHHB2bLOeC-Q","cat":"none","cdate":"Jul-26-2017 15:21:27","pdate":"2017-07-26T17:15:04Z","data":{"mission":{"gen":{"type":"Deathmatch","char":0,"endtype":0,"min":2,"mtnum":1,"num":30,"rad":0,"rank":1,"start":{"z":28.35,"x":-120.1,"y":-913.78},"subtype":0,"tnum":2,"photo":false,"icon":"Deathmatch","mode":"Deathmatch","ivm":0,"adverm":0},"rule":{"liv":0,"pol":1,"score":7,"tdm":0,"time":3,"tod":2,"traf":1,"vdm":0}},"meta":{"ems":false,"loc":[""],"veh":[-1860900134,-114291515,782665360,970385471,1233534620],"wp":[-1296747938,-546236071,779501861,792114228,1274757841,1649373715,1765114797,1948018762]}},"latest":true,"latestVersionContentId":"CpzssonmGkSHHB2bLOeC-Q","name":"moto parkour","desc":"parkour pour debuter","nickname":"--MATWARIOR--","avatar":"n/--matwarior--","rockstarId":"106177375","isOwner":false,"creatorMedal":"platinum","crewurl":"/crew/triche_de_los_santos","crewtag":"TDLS","crewrank":3,"crewcolor":"#05FF9B","isfoundercrew":false,"isprivate":true,"thumbnail":"https://prod.cloud.rockstargames.com/ugc/gta5mission/4798/CpzssonmGkSHHB2bLOeC-Q/2_0.jpg","plat":"PC","cansubscribe":false,"subscribed":false,"tags":[],"ver":1,"url":"/games/gtav/jobs/job/CpzssonmGkSHHB2bLOeC-Q","bkmk":false,"RootContentId":"CpzssonmGkSHHB2bLOeC-Q"},"stats":{"dt":0,"du":0,"pt":3,"pu":3,"qt":0,"qu":0},"ratings":{"rt_tot":0,"bkmk_unq":0,"rt_pos":2,"rt_pos_pct":1,"rt_unq":2,"rt_neg":0,"rt_neg_pct":0,"rt_avg":1,"avg":"100%"}},"Players":[]},{"MissionId":"UYoW8y_JYUiAxmvu2pP0aA","Content":{"Metadata":{"_id":"UYoW8y_JYUiAxmvu2pP0aA","cat":"none","cdate":"Jul-26-2017 11:48:44","pdate":"2017-07-26T11:48:44Z","data":{"mission":{"gen":{"type":"Race","char":0,"endtype":0,"min":1,"mtnum":1,"num":8,"rad":0,"rank":1,"start":{"z":43.47,"x":972.73,"y":-386.9},"subtype":6,"tnum":1,"photo":false,"icon":"StuntRace","mode":"Stunt Race","racetype":"Laps","ivm":0,"adverm":0},"race":{"type":"STANDARD","aveh":[],"gw":0,"chp":26,"lap":1,"rdis":2965.106,"dist":"2.97 km","ivm":0,"clbs":11263},"rule":{"liv":0,"pol":1,"score":0,"tdm":0,"time":0,"tod":0,"traf":0,"vdm":0}},"meta":{"ems":false,"loc":["EAST_V","LMESA"],"veh":[0],"vehcl":["","Industrial","Special","Vans"]}},"latest":true,"latestVersionContentId":"UYoW8y_JYUiAxmvu2pP0aA","name":"copa piston","desc":"corra","nickname":"lucas_o_gordo","avatar":"n/lucas_o_gordo","rockstarId":"104921338","isOwner":false,"creatorMedal":"silver","crewurl":"/crew/panclastas","crewtag":"PANK","crewrank":0,"crewcolor":"#779919","isfoundercrew":false,"isprivate":true,"thumbnail":"https://prod.cloud.rockstargames.com/ugc/gta5mission/2415/UYoW8y_JYUiAxmvu2pP0aA/2_0.jpg","plat":"PC","cansubscribe":false,"subscribed":false,"tags":[],"ver":1,"url":"/games/gtav/jobs/job/UYoW8y_JYUiAxmvu2pP0aA","bkmk":false,"RootContentId":"UYoW8y_JYUiAxmvu2pP0aA"},"stats":{"dt":0,"du":0,"pt":4,"pu":2,"qt":0,"qu":0},"ratings":{"rt_tot":0,"bkmk_unq":0,"rt_pos":2,"rt_pos_pct":1,"rt_unq":2,"rt_neg":0,"rt_neg_pct":0,"rt_avg":1,"avg":"100%"}},"Players":[]},{"MissionId":"WSGgZLyK00Ktll9ks017Zg","Content":{"Metadata":{"_id":"WSGgZLyK00Ktll9ks017Zg","cat":"none","cdate":"Jul-26-2017 13:02:23","pdate":"2017-07-26T13:02:23Z","data":{"mission":{"gen":{"type":"Race","char":0,"endtype":0,"min":1,"mtnum":1,"num":8,"rad":0,"rank":1,"start":{"z":23.49,"x":2674.04,"y":1680.34},"subtype":1,"tnum":1,"photo":false,"icon":"LandRaceP2P","mode":"Land Race","racetype":"Point To Point","ivm":223258115,"adverm":0},"race":{"type":"STANDARD","aveh":[],"gw":0,"chp":46,"lap":0,"rdis":2919.491,"dist":"2.92 km","ivm":0,"clbs":11263},"rule":{"liv":0,"pol":1,"score":0,"tdm":0,"time":0,"tod":1,"traf":0,"vdm":0}},"meta":{"ems":false,"loc":["ALAMO","DESRT","GRAPES","SANDY","WINDF","ZQ_UAR"],"veh":[0],"vehcl":["","Industrial","Special","Vans"]}},"latest":true,"latestVersionContentId":"WSGgZLyK00Ktll9ks017Zg","name":"Блейн.Разминка","desc":"Проедьтесь по красотам пустыни и готовьтесь к настоящим гонкам.","nickname":"LOOTER_MC_","avatar":"n/looter_mc_","rockstarId":"106039630","isOwner":false,"creatorMedal":"gold","crewrank":0,"isfoundercrew":false,"isprivate":false,"thumbnail":"https://prod.cloud.rockstargames.com/ugc/gta5mission/6270/WSGgZLyK00Ktll9ks017Zg/2_0.jpg","plat":"PC","cansubscribe":false,"subscribed":false,"tags":[],"ver":1,"url":"/games/gtav/jobs/job/WSGgZLyK00Ktll9ks017Zg","bkmk":false,"RootContentId":"WSGgZLyK00Ktll9ks017Zg"},"stats":{"dt":0,"du":0,"pt":2,"pu":2,"qt":0,"qu":0},"ratings":{"rt_tot":0,"bkmk_unq":0,"rt_pos":2,"rt_pos_pct":1,"rt_unq":2,"rt_neg":0,"rt_neg_pct":0,"rt_avg":1,"avg":"100%"}},"Players":[]},{"MissionId":"11hUXOZUW0ugADPlCaa5tw","Content":{"Metadata":{"_id":"11hUXOZUW0ugADPlCaa5tw","cat":"none","cdate":"Jul-26-2017 11:43:17","pdate":"2017-07-26T11:43:18Z","data":{"mission":{"gen":{"type":"Race","char":0,"endtype":0,"min":1,"mtnum":1,"num":8,"rad":0,"rank":1,"start":{"z":84.26,"x":1694.84,"y":1472.55},"subtype":13,"tnum":1,"photo":false,"icon":"BikeRaceP2P","mode":"Bike Race","racetype":"Point To Point","ivm":2,"adverm":0},"race":{"type":"STANDARD","aveh":[],"gw":0,"chp":7,"lap":0,"rdis":3913.098,"dist":"3.91 km","ivm":0,"clbs":8448},"rule":{"liv":0,"pol":1,"score":0,"tdm":0,"time":0,"tod":2,"traf":1,"vdm":0}},"meta":{"ems":false,"loc":["JAIL"],"veh":[0],"vehcl":["","Classics","Compacts","Coupes","Industrial","Mucle","OffRoad","Sedans","Special","Sports","Super","SUV","Utility","Vans"]}},"latest":true,"latestVersionContentId":"11hUXOZUW0ugADPlCaa5tw","name":"a prison challenge bati","desc":"stunts","nickname":"Yellok_","avatar":"n/yellok_","rockstarId":"18756973","isOwner":false,"creatorMedal":"white","crewurl":"/crew/yellocommunity","crewtag":"YECO","crewrank":0,"crewcolor":"#ffff03","isfoundercrew":false,"isprivate":true,"thumbnail":"https://prod.cloud.rockstargames.com/ugc/gta5mission/3731/11hUXOZUW0ugADPlCaa5tw/2_0.jpg","plat":"PC","cansubscribe":false,"subscribed":false,"tags":[],"ver":3,"url":"/games/gtav/jobs/job/11hUXOZUW0ugADPlCaa5tw","bkmk":false,"RootContentId":"ylqealiAk0Sq4PY36LQ34g"},"stats":{"dt":0,"du":0,"pt":2,"pu":2,"qt":4,"qu":3},"ratings":{"rt_tot":0,"bkmk_unq":0,"rt_pos":2,"rt_pos_pct":0.4,"rt_unq":5,"rt_neg":3,"rt_neg_pct":0.6,"rt_avg":0.4,"avg":"40%"}},"Players":[]},{"MissionId":"t4sNLjpPXECfzJEQACnb8Q","Content":{"Metadata":{"_id":"t4sNLjpPXECfzJEQACnb8Q","cat":"none","cdate":"Jul-26-2017 03:36:06","pdate":"2017-07-26T03:36:07Z","data":{"mission":{"gen":{"type":"Race","char":0,"endtype":0,"min":1,"mtnum":1,"num":16,"rad":0,"rank":1,"start":{"z":62.07,"x":-542.74,"y":140.46},"subtype":7,"tnum":1,"photo":false,"icon":"StuntRaceP2P","mode":"Stunt Race","racetype":"Point To Point","ivm":-631760477,"adverm":0},"race":{"type":"STANDARD","aveh":[],"gw":0,"chp":51,"lap":0,"rdis":6487.296,"dist":"6.49 km","ivm":0,"clbs":15231},"rule":{"liv":0,"pol":1,"score":0,"tdm":0,"time":0,"tod":0,"traf":1,"vdm":0}},"meta":{"ems":false,"loc":["CHIL","GREATC","ZANCUDO"],"veh":[0],"vehcl":["","Industrial","Special","Super"]}},"latest":true,"latestVersionContentId":"t4sNLjpPXECfzJEQACnb8Q","name":"小白超級坑：長程競速","desc":"小白超級坑系列","nickname":"Lestangweishi","avatar":"n/lestangweishi","rockstarId":"99681655","isOwner":false,"creatorMedal":"white","crewurl":"/crew/hellokitty_guys","crewtag":"hlkt","crewrank":4,"crewcolor":"#ff7fae","isfoundercrew":false,"isprivate":true,"thumbnail":"https://prod.cloud.rockstargames.com/ugc/gta5mission/7665/t4sNLjpPXECfzJEQACnb8Q/2_0.jpg","plat":"PC","cansubscribe":false,"subscribed":false,"tags":["小白超級"],"ver":11,"url":"/games/gtav/jobs/job/t4sNLjpPXECfzJEQACnb8Q","bkmk":false,"RootContentId":"zrSEJ_PxX0SiuglbHPtqiA"},"stats":{"dt":0,"du":0,"pt":13,"pu":4,"qt":0,"qu":0},"ratings":{"rt_tot":0,"bkmk_unq":0,"rt_pos":2,"rt_pos_pct":1,"rt_unq":2,"rt_neg":0,"rt_neg_pct":0,"rt_avg":1,"avg":"100%"}},"Players":[]},{"MissionId":"FfgTCPy0z0akTvuJoLJsaA","Content":{"Metadata":{"_id":"FfgTCPy0z0akTvuJoLJsaA","cat":"none","cdate":"Jul-26-2017 14:00:16","pdate":"2017-07-26T14:00:17Z","data":{"mission":{"gen":{"type":"FreeMission","char":0,"endtype":2,"min":2,"mtnum":1,"num":4,"rad":0,"rank":1,"start":{"z":28.35,"x":162.82,"y":-1001.97},"subtype":6,"tnum":2,"photo":false,"icon":"Capture","mode":"Capture","ivm":-1,"adverm":0},"rule":{"liv":0,"pol":1,"score":0,"tdm":0,"time":0,"tod":0,"traf":2,"vdm":0}},"meta":{"ems":false,"loc":["PBOX","SKID","WVINE"],"mrule":[0,11],"veh":[-82626025,782665360,970385471],"wp":[-1835415205,1274757841]}},"latest":true,"latestVersionContentId":"FfgTCPy0z0akTvuJoLJsaA","name":"賺錢","desc":"yee","nickname":"ddOwObb","avatar":"n/ddowobb","rockstarId":"75117414","isOwner":false,"creatorMedal":"platinum","crewurl":"/crew/grab_food_rob_lee","crewtag":"FKOB","crewrank":4,"crewcolor":"#0eed33","isfoundercrew":false,"isprivate":true,"thumbnail":"https://prod.cloud.rockstargames.com/ugc/gta5mission/6401/FfgTCPy0z0akTvuJoLJsaA/2_0.jpg","plat":"PC","cansubscribe":false,"subscribed":false,"tags":[],"ver":2,"url":"/games/gtav/jobs/job/FfgTCPy0z0akTvuJoLJsaA","bkmk":false,"RootContentId":"3xGDJ1PNNkWT4RDxY1PUtQ"},"stats":{"dt":0,"du":0,"pt":2,"pu":2,"qt":0,"qu":0},"ratings":{"rt_tot":0,"bkmk_unq":0,"rt_pos":2,"rt_pos_pct":1,"rt_unq":2,"rt_neg":0,"rt_neg_pct":0,"rt_avg":1,"avg":"100%"}},"Players":[]}]}