{"sl_translate":"model,type,mode,racetype,aveh","Count":20,"Total":720,"Missions":[{"MissionId":"UY4b_s43rkKBfPtjI2a-lg","Content":{"Metadata":{"_id":"UY4b_s43rkKBfPtjI2a-lg","cat":"none","cdate":"Jul-26-2017 14:14:52","pdate":"2017-07-26T14:14:52Z","data":{"mission":{"gen":{"type":"Race","area":{"z":0,"x":0,"y":0},"char":0,"endtype":0,"min":1,"mtnum":1,"num":8,"rad":0,"rank":1,"start":{"z":43.118,"x":7.127,"y":-748.52},"subtype":0,"tnum":1,"photo":true,"icon":"LandRace","mode":"Land Race","racetype":"Laps","ivm":0,"adverm":0},"race":{"type":"STANDARD","aveh":["Compacts","Coupes","Cycles","Motorcycles","Muscle","Off-Road","Sedans","Sports","Sports Classics","Super","SUVs","Utility"],"adlc":["7","2047","255","3","16777215","4095","16777215","2097151","1073741823","8191","0","0","0","0","0","0"],"gw":4.5,"chl":[{"x":-36.903,"y":-929.202},{"x":-280.571,"y":-847.589},{"x":-211.375,"y":-682.639},{"x":48.352,"y":-781.891},{"x":162.097,"y":-819.256},{"x":238.831,"y":-622.853},{"x":96.967,"y":-579.191},{"x":27.105,"y":-758.522}],"chp":8,"lap":1,"rdis":1569.451,"dist":"1.57 km","ivm":0,"sndchk":[{"x":0,"y":0},{"x":0,"y":0},{"x":0,"y":0},{"x":0,"y":0},{"x":0,"y":0},{"x":0,"y":0},{"x":0,"y":0},{"x":0,"y":0}],"clbs":11263},"weap":{"sub":[],"loc":[],"type":[]},"ene":{"loc":[],"model":[]},"rule":{"liv":0,"pol":1,"score":0,"tdm":0,"time":0,"tod":0,"traf":0,"vdm":0},"prop":{"loc":[],"model":[]},"dprop":{"loc":[],"model":[]},"veh":{"loc":[{"x":30.722,"y":-755.025},{"x":29.15,"y":-745.937},{"x":36.068,"y":-739.839},{"x":34.497,"y":-730.751},{"x":41.415,"y":-724.652},{"x":39.844,"y":-715.565},{"x":46.762,"y":-709.466},{"x":45.191,"y":-700.379}],"model":["Vehicle: 0","Vehicle: 0","Vehicle: 0","Vehicle: 0","Vehicle: 0","Vehicle: 0","Vehicle: 0","Vehicle: 0"]},"obj":{"loc":[],"model":[],"obb":[]},"endcon":{"dpos0":[]}},"meta":{"ems":false,"loc":[],"locn":[],"mrule":[],"stinv":[],"veh":[0],"vehcl":["Industrial","Vans","","Special"],"wp":[],"wpcl":[]}},"latest":true,"latestVersionContentId":"UY4b_s43rkKBfPtjI2a-lg","name":"gr","desc":"gg","nickname":"Excellen1038","avatar":"n/excellen1038","rockstarId":"106736590","isOwner":false,"crewrank":0,"isfoundercrew":false,"isprivate":false,"thumbnail":"https://prod.cloud.rockstargames.com/ugc/gta5mission/9564/UY4b_s43rkKBfPtjI2a-lg/2_0.jpg","plat":"PC","cansubscribe":false,"subscribed":false,"tags":[],"ver":1,"url":"/games/gtav/jobs/job/UY4b_s43rkKBfPtjI2a-lg","bkmk":false,"RootContentId":"UY4b_s43rkKBfPtjI2a-lg"}},"Players":[]},{"MissionId":"8Zw_xvzJl0SugxYAIoNX-Q","Content":{"Metadata":{"_id":"8Zw_xvzJl0SugxYAIoNX-Q","cat":"none","cdate":"Jul-26-2017 14:08:44","pdate":"2017-07-26T14:08:56Z","data":{"mission":{"gen":{"type":"Race","char":0,"endtype":0,"min":1,"mtnum":1,"num":8,"rad":0,"rank":1,"start":{"z":6.4,"x":-272.39,"y":6635.65},"subtype":6,"tnum":1,"photo":false,"icon":"StuntRace","mode":"Stunt Race","racetype":"Laps","ivm":-255678177,"adverm":0},"race":{"type":"STANDARD","aveh":[],"gw":0,"chp":13,"lap":0,"rdis":1066.387,"dist":"1.07 km","ivm":0,"clbs":11263},"rule":{"liv":0,"pol":1,"score":0,"tdm":0,"time":0,"tod":0,"traf":1,"vdm":0}},"meta":{"ems":false,"loc":["PALETO"],"veh":[0],"vehcl":["","Industrial","Special","Vans"]}},"latest":true,"latestVersionContentId":"8Zw_xvzJl0SugxYAIoNX-Q","name":"looping","desc":"une course de delire avec un maximum de looping","nickname":"marsh-malo","avatar":"n/marsh-malo","rockstarId":"105554331","isOwner":false,"crewurl":"/crew/gt_x_one","crewtag":"gtx1","crewrank":0,"crewcolor":"#03ffcd","isfoundercrew":false,"isprivate":true,"thumbnail":"https://prod.cloud.rockstargames.com/ugc/gta5mission/4968/8Zw_xvzJl0SugxYAIoNX-Q/2_0.jpg","plat":"PC","cansubscribe":false,"subscribed":false,"tags":[],"ver":1,"url":"/games/gtav/jobs/job/8Zw_xvzJl0SugxYAIoNX-Q","bkmk":false,"RootContentId":"8Zw_xvzJl0SugxYAIoNX-Q"}},"Players":[]},{"MissionId":"wcWtZNp9lECMt1BFSIyp6A","Content":{"Metadata":{"_id":"wcWtZNp9lECMt1BFSIyp6A","cat":"none","cdate":"Jul-26-2017 14:44:55","pdate":"2017-07-26T14:44:56Z","data":{"mission":{"gen":{"type":"Deathmatch","char":0,"endtype":0,"min":2,"mtnum":1,"num":30,"rad":0,"rank":1,"start":{"z":69.47,"x":-575.76,"y":5250.79},"subtype":0,"tnum":2,"photo":false,"icon":"Deathmatch","mode":"Deathmatch","ivm":0,"adverm":0},"rule":{"liv":0,"pol":1,"score":11,"tdm":0,"time":3,"tod":3,"traf":0,"vdm":0}},"meta":{"ems":false,"loc":[""],"veh":[1912215274],"wp":[483787975,1577485217,2081529176]}},"latest":true,"latestVersionContentId":"wcWtZNp9lECMt1BFSIyp6A","name":"PURGE 2# 2 BY 3RROR","desc":"purge gtasrazy","nickname":"3rror222","avatar":"n/3rror222","rockstarId":"66967696","isOwner":false,"creatorMedal":"platinum","crewurl":"/crew/gtasrazy_organizace","crewtag":"GORG","crewrank":1,"crewcolor":"#FF6633","isfoundercrew":false,"isprivate":true,"thumbnail":"https://prod.cloud.rockstargames.com/ugc/gta5mission/2277/wcWtZNp9lECMt1BFSIyp6A/2_0.jpg","plat":"PC","cansubscribe":false,"subscribed":false,"tags":[],"ver":2,"url":"/games/gtav/jobs/job/wcWtZNp9lECMt1BFSIyp6A","bkmk":false,"RootContentId":"YnxTqs09O0mydCjM36Sq7A"}},"Players":[]},{"MissionId":"j80pMfjb1EGqvM70KsPbAQ","Content":{"Metadata":{"_id":"j80pMfjb1EGqvM70KsPbAQ","cat":"none","cdate":"Jul-26-2017 14:57:27","pdate":"2017-07-26T14:57:27Z","data":{"mission":{"gen":{"type":"Race","char":0,"endtype":0,"min":1,"mtnum":1,"num":4,"rad":0,"rank":1,"start":{"z":28.2,"x":150.54,"y":-1305.83},"subtype":6,"tnum":1,"photo":false,"icon":"StuntRace","mode":"Stunt Race","racetype":"Laps","ivm":3,"adverm":0},"race":{"type":"STANDARD","aveh":[],"gw":0,"chp":10,"lap":0,"rdis":1208.535,"dist":"1.21 km","ivm":0,"clbs":320},"rule":{"liv":0,"pol":1,"score":0,"tdm":1,"time":0,"tod":2,"traf":0,"vdm":0}},"meta":{"ems":false,"loc":["DAVIS"],"veh":[0],"vehcl":["","Classics","Compacts","Coupes","Cycles","Industrial","Mucle","OffRoad","Sedans","Special","Super","SUV","Utility","Vans"]}},"latest":true,"latestVersionContentId":"j80pMfjb1EGqvM70KsPbAQ","name":"LOL","desc":"LOL","nickname":"waschbarattack","avatar":"n/waschbarattack","rockstarId":"99636104","isOwner":false,"creatorMedal":"silver","crewurl":"/crew/ign_crew","crewtag":"IGN","crewrank":1,"crewcolor":"#f99d27","isfoundercrew":false,"isprivate":false,"thumbnail":"https://prod.cloud.rockstargames.com/ugc/gta5mission/5872/j80pMfjb1EGqvM70KsPbAQ/2_0.jpg","plat":"PC","cansubscribe":false,"subscribed":false,"tags":[],"ver":1,"url":"/games/gtav/jobs/job/j80pMfjb1EGqvM70KsPbAQ","bkmk":false,"RootContentId":"j80pMfjb1EGqvM70KsPbAQ"}},"Players":[]},{"MissionId":"ofWZa_LLbUO-1VSnAgJEWQ","Content":{"Metadata":{"_id":"ofWZa_LLbUO-1VSnAgJEWQ","cat":"none","cdate":"Jul-26-2017 15:05:06","pdate":"2017-07-26T15:05:06Z","data":{"mission":{"gen":{"type":"Deathmatch","char":0,"endtype":0,"min":2,"mtnum":1,"num":12,"rad":0,"rank":1,"start":{"z":3.07,"x":-1033.76,"y":-1072.65},"subtype":1,"tnum":2,"photo":false,"icon":"TeamDeathmatch","mode":"Team Deathmatch","ivm":0,"adverm":0},"rule":{"liv":0,"pol":1,"score":2,"tdm":1,"time":1,"tod":0,"traf":1,"vdm":0}},"meta":{"ems":false,"loc":["","VCANA"],"veh":[-1403128555]}},"latest":true,"latestVersionContentId":"ofWZa_LLbUO-1VSnAgJEWQ","name":"DeathMatch 2035 v.1","desc":"Deathmatch fantastic! Zentorno..War...Gangs..Free RP and $!","nickname":"zGianfry","avatar":"n/zgianfry","rockstarId":"104068840","isOwner":false,"crewurl":"/crew/warforlife2","crewtag":"WFl2","crewrank":1,"crewcolor":"#147bdb","isfoundercrew":false,"isprivate":true,"thumbnail":"https://prod.cloud.rockstargames.com/ugc/gta5mission/8109/ofWZa_LLbUO-1VSnAgJEWQ/2_0.jpg","plat":"PC","cansubscribe":false,"subscribed":false,"tags":["gangs","war","deathmatch"],"ver":1,"url":"/games/gtav/jobs/job/ofWZa_LLbUO-1VSnAgJEWQ","bkmk":false,"RootContentId":"ofWZa_LLbUO-1VSnAgJEWQ"}},"Players":[]},{"MissionId":"1nT3dqw3Z0el64cFbQseFA","Content":{"Metadata":{"_id":"1nT3dqw3Z0el64cFbQseFA","cat":"none","cdate":"Jun-14-2017 19:09:58","pdate":"2017-07-26T15:22:04Z","data":{"mission":{"gen":{"type":"Race","char":0,"endtype":0,"min":1,"mtnum":1,"num":30,"rad":0,"rank":1,"start":{"z":103.33,"x":299.8,"y":198.42},"subtype":0,"tnum":1,"photo":false,"icon":"LandRace","mode":"Land Race","racetype":"Laps","ivm":1939284556,"adverm":0},"race":{"type":"STANDARD","aveh":[],"gw":0,"chp":14,"lap":4,"rdis":1873.109,"dist":"1.87 km","ivm":0,"clbs":11263},"rule":{"liv":0,"pol":1,"score":0,"tdm":0,"time":0,"tod":2,"traf":1,"vdm":0}},"meta":{"ems":false,"loc":["WVINE"],"veh":[0],"vehcl":["","Industrial","Special","Vans"]}},"latest":true,"latestVersionContentId":"1nT3dqw3Z0el64cFbQseFA","name":"Cinema Racetrack","desc":"Theatres and celebrities fly by in this high paced race","nickname":"FruitFreak","avatar":"n/fruitfreak","rockstarId":"48455678","isOwner":false,"creatorMedal":"gold","crewurl":"/crew/suupremee","crewtag":"easy","crewrank":4,"crewcolor":"#3399cc","isfoundercrew":false,"isprivate":true,"thumbnail":"https://prod.cloud.rockstargames.com/ugc/gta5mission/5482/1nT3dqw3Z0el64cFbQseFA/2_0.jpg","plat":"PC","cansubscribe":false,"subscribed":false,"tags":[],"ver":1,"url":"/games/gtav/jobs/job/1nT3dqw3Z0el64cFbQseFA","bkmk":false,"RootContentId":"1nT3dqw3Z0el64cFbQseFA"}},"Players":[]},{"MissionId":"2M2iUVgk40ODlCSt0g3K2g","Content":{"Metadata":{"_id":"2M2iUVgk40ODlCSt0g3K2g","cat":"none","cdate":"Jul-26-2017 15:26:07","pdate":"2017-07-26T15:26:16Z","data":{"mission":{"gen":{"type":"Deathmatch","char":0,"endtype":0,"min":2,"mtnum":1,"num":8,"rad":0,"rank":1,"start":{"z":31.3,"x":2006.43,"y":3818.23},"subtype":0,"tnum":2,"photo":false,"icon":"Deathmatch","mode":"Deathmatch","ivm":0,"adverm":0},"rule":{"liv":0,"pol":1,"score":0,"tdm":0,"time":6,"tod":0,"traf":0,"vdm":0}},"meta":{"ems":false,"loc":["","SANDY"],"veh":[-1829802492,970385471,2123327359]}},"latest":true,"latestVersionContentId":"2M2iUVgk40ODlCSt0g3K2g","name":"If Ur bored.. Play dis!","desc":"U get to play with the rocket vehicles 3","nickname":"Gta5Masterzbait","avatar":"n/gta5masterzbait","rockstarId":"107706911","isOwner":false,"crewurl":"/crew/ign_crew","crewtag":"IGN","crewrank":1,"crewcolor":"#f99d27","isfoundercrew":false,"isprivate":false,"thumbnail":"https://prod.cloud.rockstargames.com/ugc/gta5mission/8455/2M2iUVgk40ODlCSt0g3K2g/2_0.jpg","plat":"PC","cansubscribe":false,"subscribed":false,"tags":[],"ver":1,"url":"/games/gtav/jobs/job/2M2iUVgk40ODlCSt0g3K2g","bkmk":false,"RootContentId":"2M2iUVgk40ODlCSt0g3K2g"}},"Players":[]},{"MissionId":"un2vxsg9-k62bJA1tp_wsg","Content":{"Metadata":{"_id":"un2vxsg9-k62bJA1tp_wsg","cat":"none","cdate":"Jul-26-2017 16:14:39","pdate":"2017-07-26T16:15:07Z","data":{"mission":{"gen":{"type":"Race","char":0,"endtype":0,"min":1,"mtnum":1,"num":8,"rad":0,"rank":1,"start":{"z":29.33,"x":-1374.26,"y":-530.41},"subtype":0,"tnum":1,"photo":false,"icon":"LandRace","mode":"Land Race","racetype":"Laps","ivm":0,"adverm":0},"race":{"type":"STANDARD","aveh":[],"gw":0,"chp":9,"lap":0,"rdis":1063.887,"dist":"1.06 km","ivm":0,"clbs":11263},"rule":{"liv":0,"pol":1,"score":0,"tdm":0,"time":0,"tod":2,"traf":1,"vdm":0}},"meta":{"ems":false,"loc":["MORN","MOVIE","ROCKF"],"veh":[0],"vehcl":["","Industrial","Special","Vans"]}},"latest":true,"latestVersionContentId":"un2vxsg9-k62bJA1tp_wsg","name":"fast lads","desc":"go fast and stuff","nickname":"korvoley","avatar":"n/korvoley","rockstarId":"11567790","isOwner":false,"crewrank":0,"isfoundercrew":false,"isprivate":false,"thumbnail":"https://prod.cloud.rockstargames.com/ugc/gta5mission/9261/un2vxsg9-k62bJA1tp_wsg/2_0.jpg","plat":"PC","cansubscribe":false,"subscribed":false,"tags":[],"ver":1,"url":"/games/gtav/jobs/job/un2vxsg9-k62bJA1tp_wsg","bkmk":false,"RootContentId":"un2vxsg9-k62bJA1tp_wsg"}},"Players":[]},{"MissionId":"Avod1EPzek-5Hwgcz3Axvg","Content":{"Metadata":{"_id":"Avod1EPzek-5Hwgcz3Axvg","cat":"none","cdate":"Jul-26-2017 16:02:59","pdate":"2017-07-26T16:03:07Z","data":{"mission":{"gen":{"type":"Race","char":0,"endtype":0,"min":1,"mtnum":1,"num":16,"rad":0,"rank":1,"start":{"z":42.13,"x":134.38,"y":-486.4},"subtype":7,"tnum":1,"photo":false,"icon":"StuntRaceP2P","mode":"Stunt Race","racetype":"Point To Point","ivm":101905590,"adverm":0},"race":{"type":"STANDARD","aveh":[],"gw":0,"chp":54,"lap":0,"rdis":7019.976,"dist":"7.02 km","ivm":0,"clbs":512},"rule":{"liv":0,"pol":1,"score":0,"tdm":0,"time":0,"tod":2,"traf":0,"vdm":0}},"meta":{"ems":false,"loc":["ALTA","BAYTRE","BURTON","CHIL","DTVINE","OBSERV","WVINE"],"veh":[0],"vehcl":["","Bikes","Classics","Compacts","Coupes","Cycles","Industrial","Mucle","Sedans","Special","Sports","Super","SUV","Utility","Vans"]}},"latest":true,"latestVersionContentId":"Avod1EPzek-5Hwgcz3Axvg","name":"Modern Rally","desc":"Пикап Трофи!!!!! Внимательно смотрите на чекпоинти!!!! Не спешите!!","nickname":"999Pashka999","avatar":"n/999pashka999","rockstarId":"102296645","isOwner":false,"creatorMedal":"white","crewurl":"/crew/ukraine_uk","crewtag":"ukra","crewrank":3,"crewcolor":"#fff703","isfoundercrew":false,"isprivate":true,"thumbnail":"https://prod.cloud.rockstargames.com/ugc/gta5mission/6445/Avod1EPzek-5Hwgcz3Axvg/2_0.jpg","plat":"PC","cansubscribe":false,"subscribed":false,"tags":[],"ver":1,"url":"/games/gtav/jobs/job/Avod1EPzek-5Hwgcz3Axvg","bkmk":false,"RootContentId":"Avod1EPzek-5Hwgcz3Axvg"}},"Players":[]},{"MissionId":"Ge5ZHvbTdUSUaoWiJgMIfw","Content":{"Metadata":{"_id":"Ge5ZHvbTdUSUaoWiJgMIfw","cat":"none","cdate":"Jul-26-2017 14:36:18","pdate":"2017-07-26T14:50:15Z","data":{"mission":{"gen":{"type":"Race","char":0,"endtype":0,"min":1,"mtnum":1,"num":2,"rad":0,"rank":1,"start":{"z":12.94,"x":-1316.02,"y":-2183.13},"subtype":13,"tnum":1,"photo":false,"icon":"BikeRaceP2P","mode":"Bike Race","racetype":"Point To Point","ivm":1265391242,"adverm":0},"race":{"type":"STANDARD","aveh":[],"gw":0,"chp":3,"lap":0,"rdis":1149.522,"dist":"1.15 km","ivm":0,"clbs":8448},"rule":{"liv":0,"pol":1,"score":0,"tdm":0,"time":0,"tod":0,"traf":1,"vdm":0}},"meta":{"ems":false,"veh":[0],"vehcl":["","Classics","Compacts","Coupes","Industrial","Mucle","OffRoad","Sedans","Special","Sports","Super","SUV","Utility","Vans"]}},"latest":true,"latestVersionContentId":"Ge5ZHvbTdUSUaoWiJgMIfw","name":"HIPSTER SLIDE","desc":"APRENDENDO HIPSTER SLIDE","nickname":"THEKEVERSON","avatar":"n/thekeverson","rockstarId":"105569573","isOwner":false,"creatorMedal":"white","crewurl":"/crew/eg_twitch","crewtag":"EGTW","crewrank":4,"crewcolor":"#781cc9","isfoundercrew":false,"isprivate":true,"thumbnail":"https://prod.cloud.rockstargames.com/ugc/gta5mission/9769/Ge5ZHvbTdUSUaoWiJgMIfw/2_0.jpg","plat":"PC","cansubscribe":false,"subscribed":false,"tags":["hipster slide"],"ver":1,"url":"/games/gtav/jobs/job/Ge5ZHvbTdUSUaoWiJgMIfw","bkmk":false,"RootContentId":"Ge5ZHvbTdUSUaoWiJgMIfw"},"stats":{"dt":0,"du":0,"pt":0,"pu":0,"qt":1,"qu":1},"ratings":{"rt_tot":0,"bkmk_unq":1,"rt_pos":0,"rt_pos_pct":0,"rt_unq":1,"rt_neg":1,"rt_neg_pct":1,"rt_avg":0,"avg":"0%"}},"Players":[]},{"MissionId":"Yn6c7etLZ0atm4wjZL08SA","Content":{"Metadata":{"_id":"Yn6c7etLZ0atm4wjZL08SA","cat":"none","cdate":"Jul-26-2017 17:00:46","pdate":"2017-07-26T17:01:17Z","data":{"mission":{"gen":{"type":"Race","char":0,"endtype":0,"min":1,"mtnum":1,"num":10,"rad":0,"rank":1,"start":{"z":80.88,"x":1001.35,"y":5.22},"subtype":7,"tnum":1,"photo":false,"icon":"StuntRaceP2P","mode":"Stunt Race","racetype":"Point To Point","ivm":0,"adverm":0},"race":{"type":"STANDARD","aveh":[],"gw":0,"chp":44,"lap":0,"rdis":14572.8184,"dist":"14.57 km","ivm":0,"clbs":15359},"rule":{"liv":0,"pol":1,"score":0,"tdm":0,"time":0,"tod":1,"traf":0,"vdm":0}},"meta":{"ems":false,"loc":["ALAMO","CHIL","DESRT","DTVINE","EAST_V","GALLI","HARMO","RTRAK","SANCHIA","SANDY","ZANCUDO"],"veh":[0],"vehcl":["","Industrial","Special"]}},"latest":true,"latestVersionContentId":"Yn6c7etLZ0atm4wjZL08SA","name":"lcy","desc":"weixian","nickname":"lcy666sea","avatar":"n/lcy666sea","rockstarId":"93658050","isOwner":false,"crewrank":0,"isfoundercrew":false,"isprivate":false,"thumbnail":"https://prod.cloud.rockstargames.com/ugc/gta5mission/5300/Yn6c7etLZ0atm4wjZL08SA/2_0.jpg","plat":"PC","cansubscribe":false,"subscribed":false,"tags":[],"ver":1,"url":"/games/gtav/jobs/job/Yn6c7etLZ0atm4wjZL08SA","bkmk":false,"RootContentId":"Yn6c7etLZ0atm4wjZL08SA"}},"Players":[]},{"MissionId":"8rNzHyCwdEiF-dZoc7-4GA","Content":{"Metadata":{"_id":"8rNzHyCwdEiF-dZoc7-4GA","cat":"none","cdate":"Jul-26-2017 16:45:13","pdate":"2017-07-26T17:01:21Z","data":{"mission":{"gen":{"type":"Race","char":0,"endtype":0,"min":1,"mtnum":1,"num":2,"rad":0,"rank":1,"start":{"z":28.19,"x":138.51,"y":-1079.96},"subtype":6,"tnum":1,"photo":false,"icon":"StuntRace","mode":"Stunt Race","racetype":"Laps","ivm":3,"adverm":0},"race":{"type":"STANDARD","aveh":[],"gw":0,"chp":7,"lap":1,"rdis":1372.824,"dist":"1.37 km","ivm":0,"clbs":256},"rule":{"liv":0,"pol":1,"score":0,"tdm":0,"time":0,"tod":3,"traf":1,"vdm":0}},"meta":{"ems":false,"loc":["SKID"],"veh":[0],"vehcl":["","Classics","Compacts","Coupes","Cycles","Industrial","Mucle","OffRoad","Sedans","Special","Sports","Super","SUV","Utility","Vans"]}},"latest":true,"latestVersionContentId":"8rNzHyCwdEiF-dZoc7-4GA","name":"Stunt 1","desc":"Stunt f&#252;r YouTube #1","nickname":"WhitesTigerZ","avatar":"n/whitestigerz","rockstarId":"102083968","isOwner":false,"crewrank":0,"isfoundercrew":false,"isprivate":false,"thumbnail":"https://prod.cloud.rockstargames.com/ugc/gta5mission/1559/8rNzHyCwdEiF-dZoc7-4GA/2_0.jpg","plat":"PC","cansubscribe":false,"subscribed":false,"tags":[],"ver":1,"url":"/games/gtav/jobs/job/8rNzHyCwdEiF-dZoc7-4GA","bkmk":false,"RootContentId":"8rNzHyCwdEiF-dZoc7-4GA"}},"Players":[]},{"MissionId":"fbhwylQtVEq6uc-MQ2rmig","Content":{"Metadata":{"_id":"fbhwylQtVEq6uc-MQ2rmig","cat":"none","cdate":"Jul-26-2017 18:39:17","pdate":"2017-07-26T18:39:18Z","data":{"mission":{"gen":{"type":"Race","char":0,"endtype":0,"min":1,"mtnum":1,"num":2,"rad":0,"rank":1,"start":{"z":34,"x":1379.84,"y":3582.47},"subtype":6,"tnum":1,"photo":false,"icon":"StuntRace","mode":"Stunt Race","racetype":"Laps","ivm":1939284556,"adverm":0},"race":{"type":"STANDARD","aveh":[],"gw":0,"chp":12,"lap":0,"rdis":1041.306,"dist":"1.04 km","ivm":0,"clbs":11263},"rule":{"liv":0,"pol":1,"score":0,"tdm":0,"time":0,"tod":2,"traf":0,"vdm":0}},"meta":{"ems":false,"loc":["DESRT"],"veh":[0],"vehcl":["","Industrial","Special","Vans"]}},"latest":true,"latestVersionContentId":"fbhwylQtVEq6uc-MQ2rmig","name":"Samochodziki","desc":"Walka","nickname":"Szepoft","avatar":"n/szepoft","rockstarId":"97913339","isOwner":false,"creatorMedal":"white","crewrank":0,"isfoundercrew":false,"isprivate":false,"thumbnail":"https://prod.cloud.rockstargames.com/ugc/gta5mission/2284/fbhwylQtVEq6uc-MQ2rmig/2_0.jpg","plat":"PC","cansubscribe":false,"subscribed":false,"tags":[],"ver":2,"url":"/games/gtav/jobs/job/fbhwylQtVEq6uc-MQ2rmig","bkmk":false,"RootContentId":"2lr1V0iVtkGoK0rQEvlFSA"},"stats":{"dt":0,"du":0,"pt":2,"pu":1,"qt":1,"qu":1},"ratings":{"rt_tot":0,"bkmk_unq":0,"rt_pos":0,"rt_pos_pct":0,"rt_unq":1,"rt_neg":1,"rt_neg_pct":1,"rt_avg":0,"avg":"0%"}},"Players":[]},{"MissionId":"dlfadF_HQ0yX5x7VE54qvA","Content":{"Metadata":{"_id":"dlfadF_HQ0yX5x7VE54qvA","cat":"none","cdate":"Jul-26-2017 19:03:14","pdate":"2017-07-26T19:03:15Z","data":{"mission":{"gen":{"type":"Race","char":0,"endtype":0,"min":1,"mtnum":1,"num":2,"rad":0,"rank":1,"start":{"z":4.96,"x":235.26,"y":-2873.64},"subtype":5,"tnum":1,"photo":false,"icon":"AirRaceP2P","mode":"Air Race","racetype":"Point To Point","ivm":1824333165,"adverm":0},"race":{"type":"STANDARD","aveh":[],"gw":0,"chp":2,"lap":0,"rdis":2124.563,"dist":"2.12 km","ivm":0,"clbs":7},"rule":{"liv":0,"pol":1,"score":0,"tdm":0,"time":0,"tod":2,"traf":0,"vdm":0}},"meta":{"ems":false,"loc":["PBOX"],"veh":[0]}},"latest":true,"latestVersionContentId":"dlfadF_HQ0yX5x7VE54qvA","name":"опа","desc":"опаопа","nickname":"GreatGangsta125","avatar":"n/greatgangsta125","rockstarId":"78231234","isOwner":false,"creatorMedal":"white","crewurl":"/crew/tvistercrew","crewtag":"MrTv","crewrank":2,"crewcolor":"#990000","isfoundercrew":false,"isprivate":true,"thumbnail":"https://prod.cloud.rockstargames.com/ugc/gta5mission/9183/dlfadF_HQ0yX5x7VE54qvA/2_0.jpg","plat":"PC","cansubscribe":false,"subscribed":false,"tags":[],"ver":7,"url":"/games/gtav/jobs/job/dlfadF_HQ0yX5x7VE54qvA","bkmk":false,"RootContentId":"Rw9Q7IiTyUO4g640BvTW1g"},"stats":{"dt":0,"du":0,"pt":0,"pu":0,"qt":10,"qu":2},"ratings":{"rt_tot":0,"bkmk_unq":0,"rt_pos":0,"rt_pos_pct":0,"rt_unq":2,"rt_neg":2,"rt_neg_pct":1,"rt_avg":0,"avg":"0%"}},"Players":[]},{"MissionId":"Gk4fGQQZwk2Lu9wTiOoTow","Content":{"Metadata":{"_id":"Gk4fGQQZwk2Lu9wTiOoTow","cat":"none","cdate":"Jul-26-2017 19:33:32","pdate":"2017-07-26T19:33:32Z","data":{"mission":{"gen":{"type":"FreeMission","char":0,"endtype":0,"min":3,"mtnum":1,"num":15,"rad":0,"rank":1,"start":{"z":30.34,"x":899.85,"y":3702.14},"subtype":5,"tnum":3,"photo":false,"icon":"LastTeamStanding","mode":"Last Team Standing","ivm":-1,"adverm":0},"rule":{"liv":0,"pol":1,"score":0,"tdm":0,"time":0,"tod":0,"traf":2,"vdm":0}},"meta":{"ems":false,"loc":["ALAMO"],"mrule":[0,18],"veh":[-915704871]}},"latest":true,"latestVersionContentId":"Gk4fGQQZwk2Lu9wTiOoTow","name":"__DEMOLITION DERBY___","desc":"NON CAMPERATE, SALITE IN AUTO,PROSEGUITE NELLA PISTA E ENTRATE NELL&#39;ARENA,SE CADETE NELLE PIATTAFORME IN ACQUA SUICIDATEVI","nickname":"TROR04","avatar":"n/tror04","rockstarId":"97772698","isOwner":false,"creatorMedal":"silver","crewurl":"/crew/brygata-tanyno","crewtag":"BRYG","crewrank":4,"crewcolor":"#ff0303","isfoundercrew":false,"isprivate":true,"thumbnail":"https://prod.cloud.rockstargames.com/ugc/gta5mission/7422/Gk4fGQQZwk2Lu9wTiOoTow/2_0.jpg","plat":"PC","cansubscribe":false,"subscribed":false,"tags":[],"ver":1,"url":"/games/gtav/jobs/job/Gk4fGQQZwk2Lu9wTiOoTow","bkmk":false,"RootContentId":"Gk4fGQQZwk2Lu9wTiOoTow"}},"Players":[]},{"MissionId":"mgCYCX9hoEKN9LTI31MxzA","Content":{"Metadata":{"_id":"mgCYCX9hoEKN9LTI31MxzA","cat":"none","cdate":"Jul-26-2017 19:30:17","pdate":"2017-07-26T19:33:38Z","data":{"mission":{"gen":{"type":"Race","char":0,"endtype":0,"min":1,"mtnum":1,"num":12,"rad":0,"rank":1,"start":{"z":65.24,"x":-337.49,"y":-1957.12},"subtype":1,"tnum":1,"photo":false,"icon":"LandRaceP2P","mode":"Land Race","racetype":"Point To Point","ivm":1,"adverm":0},"race":{"type":"STANDARD","aveh":[],"gw":0,"chp":22,"lap":0,"rdis":1092.221,"dist":"1.09 km","ivm":0,"clbs":11263},"rule":{"liv":0,"pol":1,"score":0,"tdm":0,"time":0,"tod":3,"traf":0,"vdm":0}},"meta":{"ems":false,"veh":[0],"vehcl":["","Industrial","Special","Vans"]}},"latest":true,"latestVersionContentId":"mgCYCX9hoEKN9LTI31MxzA","name":"Nightlife 3","desc":"Good Luck ! $$$$","nickname":"mulex2000","avatar":"n/mulex2000","rockstarId":"47745488","isOwner":false,"creatorMedal":"gold","crewrank":0,"isfoundercrew":false,"isprivate":false,"thumbnail":"https://prod.cloud.rockstargames.com/ugc/gta5mission/4500/mgCYCX9hoEKN9LTI31MxzA/2_0.jpg","plat":"PC","cansubscribe":false,"subscribed":false,"tags":[],"ver":1,"url":"/games/gtav/jobs/job/mgCYCX9hoEKN9LTI31MxzA","bkmk":false,"RootContentId":"mgCYCX9hoEKN9LTI31MxzA"}},"Players":[]},{"MissionId":"5-41YOZRX0aAJ2IV5Etpdw","Content":{"Metadata":{"_id":"5-41YOZRX0aAJ2IV5Etpdw","cat":"none","cdate":"Jul-26-2017 18:49:07","pdate":"2017-07-26T18:49:12Z","data":{"mission":{"gen":{"type":"Race","char":0,"endtype":0,"min":1,"mtnum":1,"num":30,"rad":0,"rank":1,"start":{"z":26.86,"x":-1018.97,"y":-2857.5},"subtype":7,"tnum":1,"photo":false,"icon":"StuntRaceP2P","mode":"Stunt Race","racetype":"Point To Point","ivm":-1523428744,"adverm":0},"race":{"type":"STANDARD","aveh":[],"gw":0,"chp":34,"lap":0,"rdis":4459.163,"dist":"4.46 km","ivm":0,"clbs":256},"rule":{"liv":0,"pol":1,"score":0,"tdm":0,"time":0,"tod":2,"traf":1,"vdm":0}},"meta":{"ems":false,"veh":[0],"vehcl":["","Classics","Compacts","Coupes","Cycles","Industrial","Mucle","OffRoad","Sedans","Special","Sports","Super","SUV","Utility","Vans"]}},"latest":true,"latestVersionContentId":"5-41YOZRX0aAJ2IV5Etpdw","name":"STUNT MOYEN","desc":"Parcour rempli de stunts sur l&#39;a&#233;roport","nickname":"FamilyGames","avatar":"n/familygames","rockstarId":"36557472","isOwner":false,"creatorMedal":"white","crewurl":"/crew/familygamess","crewtag":"FMGm","crewrank":0,"crewcolor":"#0eeb33","isfoundercrew":false,"isprivate":true,"thumbnail":"https://prod.cloud.rockstargames.com/ugc/gta5mission/5646/5-41YOZRX0aAJ2IV5Etpdw/2_0.jpg","plat":"PC","cansubscribe":false,"subscribed":false,"tags":[],"ver":2,"url":"/games/gtav/jobs/job/5-41YOZRX0aAJ2IV5Etpdw","bkmk":false,"RootContentId":"zxyNG5uch0i6WcGZIrUSOw"},"stats":{"dt":0,"du":0,"pt":0,"pu":0,"qt":7,"qu":5},"ratings":{"rt_tot":0,"bkmk_unq":0,"rt_pos":0,"rt_pos_pct":0,"rt_unq":5,"rt_neg":5,"rt_neg_pct":1,"rt_avg":0,"avg":"0%"}},"Players":[]},{"MissionId":"1KFB5raxvUaI1ohfggQuSQ","Content":{"Metadata":{"_id":"1KFB5raxvUaI1ohfggQuSQ","cat":"none","cdate":"Jul-26-2017 07:20:12","pdate":"2017-07-26T07:20:16Z","data":{"mission":{"gen":{"type":"Race","char":0,"endtype":0,"min":1,"mtnum":1,"num":12,"rad":0,"rank":1,"start":{"z":21.27,"x":714.32,"y":-1070.52},"subtype":7,"tnum":1,"photo":false,"icon":"StuntRaceP2P","mode":"Stunt Race","racetype":"Point To Point","ivm":196747873,"adverm":0},"race":{"type":"STANDARD","aveh":[],"gw":0,"chp":36,"lap":0,"rdis":4706.479,"dist":"4.71 km","ivm":0,"clbs":11263},"rule":{"liv":0,"pol":1,"score":0,"tdm":0,"time":0,"tod":0,"traf":0,"vdm":0}},"meta":{"ems":false,"loc":["KOREAT","MURRI","PBOX","STRAW"],"veh":[0],"vehcl":["","Industrial","Special","Vans"]}},"latest":true,"latestVersionContentId":"1KFB5raxvUaI1ohfggQuSQ","name":"(X) Street Point to Point","desc":"Poop","nickname":"Kurt_Mustang","avatar":"n/kurt_mustang","rockstarId":"30205949","isOwner":false,"creatorMedal":"platinum","crewurl":"/crew/zero_period","crewtag":"ZERO","crewrank":4,"crewcolor":"#c20202","isfoundercrew":false,"isprivate":true,"thumbnail":"https://prod.cloud.rockstargames.com/ugc/gta5mission/2036/1KFB5raxvUaI1ohfggQuSQ/2_0.jpg","plat":"PC","cansubscribe":false,"subscribed":false,"tags":[],"ver":1,"url":"/games/gtav/jobs/job/1KFB5raxvUaI1ohfggQuSQ","bkmk":false,"RootContentId":"1KFB5raxvUaI1ohfggQuSQ"}},"Players":[]},{"MissionId":"lyB-w4cxkE2O0SQP97nSvA","Content":{"Metadata":{"_id":"lyB-w4cxkE2O0SQP97nSvA","cat":"none","cdate":"Jul-26-2017 08:40:43","pdate":"2017-07-26T08:40:52Z","data":{"mission":{"gen":{"type":"Deathmatch","char":0,"endtype":0,"min":2,"mtnum":1,"num":20,"rad":0,"rank":1,"start":{"z":8.22,"x":-1696.49,"y":-832.33},"subtype":0,"tnum":2,"photo":false,"icon":"Deathmatch","mode":"Deathmatch","ivm":0,"adverm":0},"rule":{"liv":0,"pol":1,"score":7,"tdm":0,"time":6,"tod":0,"traf":1,"vdm":0}},"meta":{"ems":false,"loc":["","DELBE"],"veh":[-2048333973,-1758137366,782665360,1093792632,2067820283],"wp":[-2124585240,-2050315855,-1989692173,-1888453608,-1766583645,-1456120371,-1298986476,-1296747938,-1118969278,-546236071,-336028321,-253098439,-214137936,-105925489,-30788308,157823901,266812085,779501861,996550793,1632369836,1817941018]}},"latest":true,"latestVersionContentId":"lyB-w4cxkE2O0SQP97nSvA","name":"Pakuś i Duna","desc":"taki śmieszny dedmecz* hihi to specikalnie ten błąd","nickname":"GTA4fun07","avatar":"n/gta4fun07","rockstarId":"85063298","isOwner":false,"creatorMedal":"white","crewurl":"/crew/polska_sila_k","crewtag":"posk","crewrank":4,"crewcolor":"#000000AA","isfoundercrew":false,"isprivate":true,"thumbnail":"https://prod.cloud.rockstargames.com/ugc/gta5mission/0988/lyB-w4cxkE2O0SQP97nSvA/2_0.jpg","plat":"PC","cansubscribe":false,"subscribed":false,"tags":[],"ver":1,"url":"/games/gtav/jobs/job/lyB-w4cxkE2O0SQP97nSvA","bkmk":false,"RootContentId":"lyB-w4cxkE2O0SQP97nSvA"}},"Players":[]},{"MissionId":"gXXXig2GRU6wCD2-MvKu4w","Content":{"Metadata":{"_id":"gXXXig2GRU6wCD2-MvKu4w","cat":"none","cdate":"Jul-26-2017 07:03:20","pdate":"2017-07-26T07:03:35Z","data":{"mission":{"gen":{"type":"Race","char":0,"endtype":0,"min":1,"mtnum":1,"num":10,"rad":0,"rank":1,"start":{"z":10.34,"x":-1281.33,"y":-1368.52},"subtype":7,"tnum":1,"photo":false,"icon":"StuntRaceP2P","mode":"Stunt Race","racetype":"Point To Point","ivm":0,"adverm":0},"race":{"type":"STANDARD","aveh":[],"gw":0,"chp":15,"lap":0,"rdis":2677.501,"dist":"2.68 km","ivm":0,"clbs":8448},"rule":{"liv":0,"pol":1,"score":0,"tdm":0,"time":0,"tod":2,"traf":1,"vdm":0}},"meta":{"ems":false,"loc":["BEACH","DELSOL","LOSPUER","STAD","VCANA"],"veh":[0],"vehcl":["","Classics","Compacts","Coupes","Industrial","Mucle","OffRoad","Sedans","Special","Sports","Super","SUV","Utility","Vans"]}},"latest":true,"latestVersionContentId":"gXXXig2GRU6wCD2-MvKu4w","name":"МОТО-PARKOUR","desc":"Parkour на MOTO","nickname":"XxX_XeX_XxX","avatar":"n/xxx_xex_xxx","rockstarId":"106622044","isOwner":false,"crewrank":0,"isfoundercrew":false,"isprivate":false,"thumbnail":"https://prod.cloud.rockstargames.com/ugc/gta5mission/7301/gXXXig2GRU6wCD2-MvKu4w/2_0.jpg","plat":"PC","cansubscribe":false,"subscribed":false,"tags":["moto","parkour","мотоциклы"],"ver":1,"url":"/games/gtav/jobs/job/gXXXig2GRU6wCD2-MvKu4w","bkmk":false,"RootContentId":"gXXXig2GRU6wCD2-MvKu4w"}},"Players":[]}]}